Classfile /u0/j523xu/scala3/out/bcGen/Classes/Nested1$Inner1$Inner2_0.class
  Last modified Oct 16, 2025; size 2396 bytes
  SHA-256 checksum 7bc5b9736660aa6c91359a4fd7f0520fa511ec8071e58559e49ac02bd87f57d5
  Compiled from "Nested1.scala"
public class bcGen.Classes.Nested1$Inner1$Inner2_0<V extends java.lang.Object> extends bcGen.Classes.Pair<T, U>
  minor version: 0
  major version: 52
  flags: (0x0021) ACC_PUBLIC, ACC_SUPER
  this_class: #2                          // bcGen/Classes/Nested1$Inner1$Inner2_0
  super_class: #5                         // bcGen/Classes/Pair
  interfaces: 0, fields: 3, methods: 6, attributes: 5
Constant pool:
    #1 = Utf8               bcGen/Classes/Nested1$Inner1$Inner2_0
    #2 = Class              #1            // bcGen/Classes/Nested1$Inner1$Inner2_0
    #3 = Utf8               <V:Ljava/lang/Object;>LbcGen/Classes/Pair<TT;TU;>;
    #4 = Utf8               bcGen/Classes/Pair
    #5 = Class              #4            // bcGen/Classes/Pair
    #6 = Utf8               Nested1.scala
    #7 = Utf8               bcGen/Classes/Nested1$Inner1
    #8 = Class              #7            // bcGen/Classes/Nested1$Inner1
    #9 = Utf8               bcGen/Classes/Nested1
   #10 = Class              #9            // bcGen/Classes/Nested1
   #11 = Utf8               Inner1
   #12 = Utf8               Inner2_0
   #13 = Utf8               initInner2V
   #14 = Utf8               Ljava/lang/Object;
   #15 = Utf8               TV;
   #16 = Utf8               inner2_0V
   #17 = Utf8               $outer
   #18 = Utf8               LbcGen/Classes/Nested1$Inner1;
   #19 = Utf8               <init>
   #20 = Utf8               (LbcGen/Classes/Nested1$Inner1;Ljava/lang/Object;)V
   #21 = Utf8               (TV;)V
   #22 = NameAndType        #13:#14       // initInner2V:Ljava/lang/Object;
   #23 = Fieldref           #2.#22        // bcGen/Classes/Nested1$Inner1$Inner2_0.initInner2V:Ljava/lang/Object;
   #24 = Utf8               java/lang/NullPointerException
   #25 = Class              #24           // java/lang/NullPointerException
   #26 = Utf8               ()V
   #27 = NameAndType        #19:#26       // "<init>":()V
   #28 = Methodref          #25.#27       // java/lang/NullPointerException."<init>":()V
   #29 = NameAndType        #17:#18       // $outer:LbcGen/Classes/Nested1$Inner1;
   #30 = Fieldref           #2.#29        // bcGen/Classes/Nested1$Inner1$Inner2_0.$outer:LbcGen/Classes/Nested1$Inner1;
   #31 = Utf8               bcGen$Classes$Nested1$Inner1$$$outer
   #32 = Utf8               ()LbcGen/Classes/Nested1;
   #33 = NameAndType        #31:#32       // bcGen$Classes$Nested1$Inner1$$$outer:()LbcGen/Classes/Nested1;
   #34 = Methodref          #8.#33        // bcGen/Classes/Nested1$Inner1.bcGen$Classes$Nested1$Inner1$$$outer:()LbcGen/Classes/Nested1;
   #35 = Utf8               outer1T
   #36 = Utf8               ()Ljava/lang/Object;
   #37 = NameAndType        #35:#36       // outer1T:()Ljava/lang/Object;
   #38 = Methodref          #10.#37       // bcGen/Classes/Nested1.outer1T:()Ljava/lang/Object;
   #39 = Utf8               inner1U
   #40 = NameAndType        #39:#36       // inner1U:()Ljava/lang/Object;
   #41 = Methodref          #8.#40        // bcGen/Classes/Nested1$Inner1.inner1U:()Ljava/lang/Object;
   #42 = Utf8               (Ljava/lang/Object;Ljava/lang/Object;)V
   #43 = NameAndType        #19:#42       // "<init>":(Ljava/lang/Object;Ljava/lang/Object;)V
   #44 = Methodref          #5.#43        // bcGen/Classes/Pair."<init>":(Ljava/lang/Object;Ljava/lang/Object;)V
   #45 = NameAndType        #16:#14       // inner2_0V:Ljava/lang/Object;
   #46 = Fieldref           #2.#45        // bcGen/Classes/Nested1$Inner1$Inner2_0.inner2_0V:Ljava/lang/Object;
   #47 = Utf8               this
   #48 = Utf8               LbcGen/Classes/Nested1$Inner1$Inner2_0;
   #49 = Utf8               ()TV;
   #50 = Utf8               foo
   #51 = Utf8               (Ljava/lang/Object;Ljava/lang/Object;Ljava/lang/Object;)Ljava/lang/String;
   #52 = Utf8               (TT;TU;TV;)Ljava/lang/String;
   #53 = Utf8               x
   #54 = Utf8               y
   #55 = Utf8               z
   #56 = Utf8               java/lang/StringBuilder
   #57 = Class              #56           // java/lang/StringBuilder
   #58 = Integer            28
   #59 = Utf8               (I)V
   #60 = NameAndType        #19:#59       // "<init>":(I)V
   #61 = Methodref          #57.#60       // java/lang/StringBuilder."<init>":(I)V
   #62 = Utf8               Outer1:
   #63 = String             #62           // Outer1:
   #64 = Utf8               append
   #65 = Utf8               (Ljava/lang/String;)Ljava/lang/StringBuilder;
   #66 = NameAndType        #64:#65       // append:(Ljava/lang/String;)Ljava/lang/StringBuilder;
   #67 = Methodref          #57.#66       // java/lang/StringBuilder.append:(Ljava/lang/String;)Ljava/lang/StringBuilder;
   #68 = Utf8               (Ljava/lang/Object;)Ljava/lang/StringBuilder;
   #69 = NameAndType        #64:#68       // append:(Ljava/lang/Object;)Ljava/lang/StringBuilder;
   #70 = Methodref          #57.#69       // java/lang/StringBuilder.append:(Ljava/lang/Object;)Ljava/lang/StringBuilder;
   #71 = Utf8               , Inner1:
   #72 = String             #71           // , Inner1:
   #73 = Utf8               , Inner2:
   #74 = String             #73           // , Inner2:
   #75 = Utf8               toString
   #76 = Utf8               ()Ljava/lang/String;
   #77 = NameAndType        #75:#76       // toString:()Ljava/lang/String;
   #78 = Methodref          #57.#77       // java/lang/StringBuilder.toString:()Ljava/lang/String;
   #79 = Utf8               bar
   #80 = NameAndType        #16:#36       // inner2_0V:()Ljava/lang/Object;
   #81 = Methodref          #2.#80        // bcGen/Classes/Nested1$Inner1$Inner2_0.inner2_0V:()Ljava/lang/Object;
   #82 = Utf8               bcGen$Classes$Nested1$Inner1$Inner2_0$$$outer
   #83 = Utf8               ()LbcGen/Classes/Nested1$Inner1;
   #84 = Utf8               Signature
   #85 = Utf8               FieldType
   #86 = Utf8               Code
   #87 = Utf8               StackMapTable
   #88 = Utf8               LineNumberTable
   #89 = Utf8               LocalVariableTable
   #90 = Utf8               MethodParameters
   #91 = Utf8               InstructionTypeArguments
   #92 = Utf8               InvokeReturnType
   #93 = Utf8               MethodParameterType
   #94 = Utf8               MethodTypeParameterCount
   #95 = Utf8               MethodReturnType
   #96 = Utf8               InnerClasses
   #97 = Utf8               SourceFile
   #98 = Utf8               ClassTypeParameterCount
   #99 = Utf8               Scala
{
  private final V initInner2V;
    descriptor: Ljava/lang/Object;
    flags: (0x0012) ACC_PRIVATE, ACC_FINAL
    Signature: #15                          // TV;
      FieldType: length = 0x5 (unknown attribute)
       4B 00 00 00 00

  private final V inner2_0V;
    descriptor: Ljava/lang/Object;
    flags: (0x0012) ACC_PRIVATE, ACC_FINAL
    Signature: #15                          // TV;
      FieldType: length = 0x5 (unknown attribute)
       4B 00 00 00 00

  private final bcGen.Classes.Nested1$Inner1 $outer;
    descriptor: LbcGen/Classes/Nested1$Inner1;
    flags: (0x1012) ACC_PRIVATE, ACC_FINAL, ACC_SYNTHETIC

  public bcGen.Classes.Nested1$Inner1$Inner2_0(V);
    descriptor: (LbcGen/Classes/Nested1$Inner1;Ljava/lang/Object;)V
    flags: (0x0001) ACC_PUBLIC
    Code:
      stack=3, locals=3, args_size=3
         0: aload_0
         1: aload_2
         2: putfield      #23                 // Field initInner2V:Ljava/lang/Object;
         5: aload_1
         6: ifnonnull     17
         9: new           #25                 // class java/lang/NullPointerException
        12: dup
        13: invokespecial #28                 // Method java/lang/NullPointerException."<init>":()V
        16: athrow
        17: aload_0
        18: aload_1
        19: putfield      #30                 // Field $outer:LbcGen/Classes/Nested1$Inner1;
        22: aload_0
        23: aload_1
        24: invokevirtual #34                 // Method bcGen/Classes/Nested1$Inner1.bcGen$Classes$Nested1$Inner1$$$outer:()LbcGen/Classes/Nested1;
        27: invokevirtual #38                 // Method bcGen/Classes/Nested1.outer1T:()Ljava/lang/Object;
        30: aload_1
        31: invokevirtual #41                 // Method bcGen/Classes/Nested1$Inner1.inner1U:()Ljava/lang/Object;
        34: invokespecial #44                 // Method bcGen/Classes/Pair."<init>":(Ljava/lang/Object;Ljava/lang/Object;)V
        37: aload_0
        38: aload_2
        39: putfield      #46                 // Field inner2_0V:Ljava/lang/Object;
        42: return
      StackMapTable: number_of_entries = 1
        frame_type = 17 /* same */
      LineNumberTable:
        line 8: 0
        line 11: 5
        line 8: 17
        line 9: 37
      LocalVariableTable:
        Start  Length  Slot  Name   Signature
            0      43     0  this   LbcGen/Classes/Nested1$Inner1$Inner2_0;
            0      43     1 $outer   LbcGen/Classes/Nested1$Inner1;
            0      43     2 initInner2V   Ljava/lang/Object;
    Signature: #21                          // (TV;)V
    MethodParameters:
      Name                           Flags
      $outer                         final synthetic
      initInner2V                    final
      InstructionTypeArguments: length = 0x10 (unknown attribute)
       00 01 00 22 00 02 4B 00 02 00 00 4B 00 01 00 00

      InvokeReturnType: length = 0x10 (unknown attribute)
       00 02 00 1B 4B 00 02 00 00 00 1F 4B 00 01 00 00

      MethodParameterType: length = 0x7 (unknown attribute)
       00 01 4D 00 00 00 00
      MethodTypeParameterCount: length = 0x2 (unknown attribute)
       00 01

  public V initInner2V();
    descriptor: ()Ljava/lang/Object;
    flags: (0x0001) ACC_PUBLIC
    Code:
      stack=1, locals=1, args_size=1
         0: aload_0
         1: getfield      #23                 // Field initInner2V:Ljava/lang/Object;
         4: areturn
      LineNumberTable:
        line 8: 0
      LocalVariableTable:
        Start  Length  Slot  Name   Signature
            0       5     0  this   LbcGen/Classes/Nested1$Inner1$Inner2_0;
    Signature: #49                          // ()TV;
      MethodReturnType: length = 0x5 (unknown attribute)
       4B 00 00 00 00

  public V inner2_0V();
    descriptor: ()Ljava/lang/Object;
    flags: (0x0001) ACC_PUBLIC
    Code:
      stack=1, locals=1, args_size=1
         0: aload_0
         1: getfield      #46                 // Field inner2_0V:Ljava/lang/Object;
         4: areturn
      LineNumberTable:
        line 9: 0
      LocalVariableTable:
        Start  Length  Slot  Name   Signature
            0       5     0  this   LbcGen/Classes/Nested1$Inner1$Inner2_0;
    Signature: #49                          // ()TV;
      MethodReturnType: length = 0x5 (unknown attribute)
       4B 00 00 00 00

  public java.lang.String foo(T, U, V);
    descriptor: (Ljava/lang/Object;Ljava/lang/Object;Ljava/lang/Object;)Ljava/lang/String;
    flags: (0x0001) ACC_PUBLIC
    Code:
      stack=3, locals=4, args_size=4
         0: new           #57                 // class java/lang/StringBuilder
         3: dup
         4: ldc           #58                 // int 28
         6: invokespecial #61                 // Method java/lang/StringBuilder."<init>":(I)V
         9: ldc           #63                 // String Outer1:
        11: invokevirtual #67                 // Method java/lang/StringBuilder.append:(Ljava/lang/String;)Ljava/lang/StringBuilder;
        14: aload_1
        15: invokevirtual #70                 // Method java/lang/StringBuilder.append:(Ljava/lang/Object;)Ljava/lang/StringBuilder;
        18: ldc           #72                 // String , Inner1:
        20: invokevirtual #67                 // Method java/lang/StringBuilder.append:(Ljava/lang/String;)Ljava/lang/StringBuilder;
        23: aload_2
        24: invokevirtual #70                 // Method java/lang/StringBuilder.append:(Ljava/lang/Object;)Ljava/lang/StringBuilder;
        27: ldc           #74                 // String , Inner2:
        29: invokevirtual #67                 // Method java/lang/StringBuilder.append:(Ljava/lang/String;)Ljava/lang/StringBuilder;
        32: aload_3
        33: invokevirtual #70                 // Method java/lang/StringBuilder.append:(Ljava/lang/Object;)Ljava/lang/StringBuilder;
        36: invokevirtual #78                 // Method java/lang/StringBuilder.toString:()Ljava/lang/String;
        39: areturn
      LineNumberTable:
        line 10: 0
      LocalVariableTable:
        Start  Length  Slot  Name   Signature
            0      40     0  this   LbcGen/Classes/Nested1$Inner1$Inner2_0;
            0      40     1     x   Ljava/lang/Object;
            0      40     2     y   Ljava/lang/Object;
            0      40     3     z   Ljava/lang/Object;
    Signature: #52                          // (TT;TU;TV;)Ljava/lang/String;
    MethodParameters:
      Name                           Flags
      x                              final
      y                              final
      z                              final
      MethodParameterType: length = 0x11 (unknown attribute)
       00 03 4B 00 02 00 00 4B 00 01 00 00 4B 00 00 00
       00

  public java.lang.String bar();
    descriptor: ()Ljava/lang/String;
    flags: (0x0001) ACC_PUBLIC
    Code:
      stack=3, locals=1, args_size=1
         0: new           #57                 // class java/lang/StringBuilder
         3: dup
         4: ldc           #58                 // int 28
         6: invokespecial #61                 // Method java/lang/StringBuilder."<init>":(I)V
         9: ldc           #63                 // String Outer1:
        11: invokevirtual #67                 // Method java/lang/StringBuilder.append:(Ljava/lang/String;)Ljava/lang/StringBuilder;
        14: aload_0
        15: getfield      #30                 // Field $outer:LbcGen/Classes/Nested1$Inner1;
        18: invokevirtual #34                 // Method bcGen/Classes/Nested1$Inner1.bcGen$Classes$Nested1$Inner1$$$outer:()LbcGen/Classes/Nested1;
        21: invokevirtual #38                 // Method bcGen/Classes/Nested1.outer1T:()Ljava/lang/Object;
        24: invokevirtual #70                 // Method java/lang/StringBuilder.append:(Ljava/lang/Object;)Ljava/lang/StringBuilder;
        27: ldc           #72                 // String , Inner1:
        29: invokevirtual #67                 // Method java/lang/StringBuilder.append:(Ljava/lang/String;)Ljava/lang/StringBuilder;
        32: aload_0
        33: getfield      #30                 // Field $outer:LbcGen/Classes/Nested1$Inner1;
        36: invokevirtual #41                 // Method bcGen/Classes/Nested1$Inner1.inner1U:()Ljava/lang/Object;
        39: invokevirtual #70                 // Method java/lang/StringBuilder.append:(Ljava/lang/Object;)Ljava/lang/StringBuilder;
        42: ldc           #74                 // String , Inner2:
        44: invokevirtual #67                 // Method java/lang/StringBuilder.append:(Ljava/lang/String;)Ljava/lang/StringBuilder;
        47: aload_0
        48: invokevirtual #81                 // Method inner2_0V:()Ljava/lang/Object;
        51: invokevirtual #70                 // Method java/lang/StringBuilder.append:(Ljava/lang/Object;)Ljava/lang/StringBuilder;
        54: invokevirtual #78                 // Method java/lang/StringBuilder.toString:()Ljava/lang/String;
        57: areturn
      LineNumberTable:
        line 11: 0
      LocalVariableTable:
        Start  Length  Slot  Name   Signature
            0      58     0  this   LbcGen/Classes/Nested1$Inner1$Inner2_0;
      InvokeReturnType: length = 0x17 (unknown attribute)
       00 03 00 15 4B 00 02 00 00 00 24 4B 00 01 00 00
       00 30 4B 00 00 00 00

  public final bcGen.Classes.Nested1$Inner1 bcGen$Classes$Nested1$Inner1$Inner2_0$$$outer();
    descriptor: ()LbcGen/Classes/Nested1$Inner1;
    flags: (0x1011) ACC_PUBLIC, ACC_FINAL, ACC_SYNTHETIC
    Code:
      stack=1, locals=1, args_size=1
         0: aload_0
         1: getfield      #30                 // Field $outer:LbcGen/Classes/Nested1$Inner1;
         4: areturn
      LineNumberTable:
        line 11: 0
      LocalVariableTable:
        Start  Length  Slot  Name   Signature
            0       5     0  this   LbcGen/Classes/Nested1$Inner1$Inner2_0;
}
InnerClasses:
  public #11= #8 of #10;                  // Inner1=class bcGen/Classes/Nested1$Inner1 of class bcGen/Classes/Nested1
  public #12= #2 of #8;                   // Inner2_0=class bcGen/Classes/Nested1$Inner1$Inner2_0 of class bcGen/Classes/Nested1$Inner1
Signature: #3                           // <V:Ljava/lang/Object;>LbcGen/Classes/Pair<TT;TU;>;
SourceFile: "Nested1.scala"
  ClassTypeParameterCount: length = 0x2 (unknown attribute)
   00 01
  Scala: length = 0x0 (unknown attribute)

