Classfile /u0/j523xu/scala3/out/bcGen/Classes/testPair$.class
  Last modified Oct 16, 2025; size 2787 bytes
  SHA-256 checksum 97d7aee34e360baf4f66636a307ad0c23f5138c4d36d40680e48657fe9a5fcd3
  Compiled from "Pair.scala"
public final class bcGen.Classes.testPair$ implements java.io.Serializable
  minor version: 0
  major version: 52
  flags: (0x0031) ACC_PUBLIC, ACC_FINAL, ACC_SUPER
  this_class: #2                          // bcGen/Classes/testPair$
  super_class: #4                         // java/lang/Object
  interfaces: 1, fields: 4, methods: 9, attributes: 2
Constant pool:
    #1 = Utf8               bcGen/Classes/testPair$
    #2 = Class              #1            // bcGen/Classes/testPair$
    #3 = Utf8               java/lang/Object
    #4 = Class              #3            // java/lang/Object
    #5 = Utf8               java/io/Serializable
    #6 = Class              #5            // java/io/Serializable
    #7 = Utf8               Pair.scala
    #8 = Utf8               intRefPair
    #9 = Utf8               LbcGen/Classes/Pair;
   #10 = Utf8               LbcGen/Classes/Pair<Ljava/lang/Object;Ljava/lang/String;>;
   #11 = Utf8               doubleLongPair
   #12 = Utf8               LbcGen/Classes/Pair<Ljava/lang/Object;Ljava/lang/Object;>;
   #13 = Utf8               anyAnyPair
   #14 = Utf8               MODULE$
   #15 = Utf8               LbcGen/Classes/testPair$;
   #16 = Utf8               <init>
   #17 = Utf8               ()V
   #18 = NameAndType        #16:#17       // "<init>":()V
   #19 = Methodref          #4.#18        // java/lang/Object."<init>":()V
   #20 = Utf8               this
   #21 = Utf8               <clinit>
   #22 = Methodref          #2.#18        // bcGen/Classes/testPair$."<init>":()V
   #23 = NameAndType        #14:#15       // MODULE$:LbcGen/Classes/testPair$;
   #24 = Fieldref           #2.#23        // bcGen/Classes/testPair$.MODULE$:LbcGen/Classes/testPair$;
   #25 = Utf8               bcGen/Classes/Pair
   #26 = Class              #25           // bcGen/Classes/Pair
   #27 = Utf8               scala/runtime/BoxesRunTime
   #28 = Class              #27           // scala/runtime/BoxesRunTime
   #29 = Utf8               boxToInteger
   #30 = Utf8               (I)Ljava/lang/Integer;
   #31 = NameAndType        #29:#30       // boxToInteger:(I)Ljava/lang/Integer;
   #32 = Methodref          #28.#31       // scala/runtime/BoxesRunTime.boxToInteger:(I)Ljava/lang/Integer;
   #33 = Utf8               one
   #34 = String             #33           // one
   #35 = Utf8               (Ljava/lang/Object;Ljava/lang/Object;)V
   #36 = NameAndType        #16:#35       // "<init>":(Ljava/lang/Object;Ljava/lang/Object;)V
   #37 = Methodref          #26.#36       // bcGen/Classes/Pair."<init>":(Ljava/lang/Object;Ljava/lang/Object;)V
   #38 = NameAndType        #8:#9         // intRefPair:LbcGen/Classes/Pair;
   #39 = Fieldref           #2.#38        // bcGen/Classes/testPair$.intRefPair:LbcGen/Classes/Pair;
   #40 = Double             3.14d
   #42 = Utf8               boxToDouble
   #43 = Utf8               (D)Ljava/lang/Double;
   #44 = NameAndType        #42:#43       // boxToDouble:(D)Ljava/lang/Double;
   #45 = Methodref          #28.#44       // scala/runtime/BoxesRunTime.boxToDouble:(D)Ljava/lang/Double;
   #46 = Long               42l
   #48 = Utf8               boxToLong
   #49 = Utf8               (J)Ljava/lang/Long;
   #50 = NameAndType        #48:#49       // boxToLong:(J)Ljava/lang/Long;
   #51 = Methodref          #28.#50       // scala/runtime/BoxesRunTime.boxToLong:(J)Ljava/lang/Long;
   #52 = NameAndType        #11:#9        // doubleLongPair:LbcGen/Classes/Pair;
   #53 = Fieldref           #2.#52        // bcGen/Classes/testPair$.doubleLongPair:LbcGen/Classes/Pair;
   #54 = Utf8               key
   #55 = String             #54           // key
   #56 = NameAndType        #13:#9        // anyAnyPair:LbcGen/Classes/Pair;
   #57 = Fieldref           #2.#56        // bcGen/Classes/testPair$.anyAnyPair:LbcGen/Classes/Pair;
   #58 = Utf8               writeReplace
   #59 = Utf8               ()Ljava/lang/Object;
   #60 = Utf8               scala/runtime/ModuleSerializationProxy
   #61 = Class              #60           // scala/runtime/ModuleSerializationProxy
   #62 = Utf8               (Ljava/lang/Class;)V
   #63 = NameAndType        #16:#62       // "<init>":(Ljava/lang/Class;)V
   #64 = Methodref          #61.#63       // scala/runtime/ModuleSerializationProxy."<init>":(Ljava/lang/Class;)V
   #65 = Utf8               ()LbcGen/Classes/Pair;
   #66 = Utf8               ()LbcGen/Classes/Pair<Ljava/lang/Object;Ljava/lang/String;>;
   #67 = Utf8               ()LbcGen/Classes/Pair<Ljava/lang/Object;Ljava/lang/Object;>;
   #68 = Utf8               passGenericPair
   #69 = Utf8               (LbcGen/Classes/Pair;)Ljava/lang/String;
   #70 = Utf8               <K:Ljava/lang/Object;V:Ljava/lang/Object;>(LbcGen/Classes/Pair<TK;TV;>;)Ljava/lang/String;
   #71 = Utf8               pair
   #72 = Utf8               java/lang/StringBuilder
   #73 = Class              #72           // java/lang/StringBuilder
   #74 = Integer            29
   #75 = Utf8               (I)V
   #76 = NameAndType        #16:#75       // "<init>":(I)V
   #77 = Methodref          #73.#76       // java/lang/StringBuilder."<init>":(I)V
   #78 = Utf8               Generic Pair - Key:
   #79 = String             #78           // Generic Pair - Key:
   #80 = Utf8               append
   #81 = Utf8               (Ljava/lang/String;)Ljava/lang/StringBuilder;
   #82 = NameAndType        #80:#81       // append:(Ljava/lang/String;)Ljava/lang/StringBuilder;
   #83 = Methodref          #73.#82       // java/lang/StringBuilder.append:(Ljava/lang/String;)Ljava/lang/StringBuilder;
   #84 = Utf8               getKey
   #85 = NameAndType        #84:#59       // getKey:()Ljava/lang/Object;
   #86 = Methodref          #26.#85       // bcGen/Classes/Pair.getKey:()Ljava/lang/Object;
   #87 = Utf8               (Ljava/lang/Object;)Ljava/lang/StringBuilder;
   #88 = NameAndType        #80:#87       // append:(Ljava/lang/Object;)Ljava/lang/StringBuilder;
   #89 = Methodref          #73.#88       // java/lang/StringBuilder.append:(Ljava/lang/Object;)Ljava/lang/StringBuilder;
   #90 = Utf8               , Value:
   #91 = String             #90           // , Value:
   #92 = Utf8               getValue
   #93 = NameAndType        #92:#59       // getValue:()Ljava/lang/Object;
   #94 = Methodref          #26.#93       // bcGen/Classes/Pair.getValue:()Ljava/lang/Object;
   #95 = Utf8               toString
   #96 = Utf8               ()Ljava/lang/String;
   #97 = NameAndType        #95:#96       // toString:()Ljava/lang/String;
   #98 = Methodref          #73.#97       // java/lang/StringBuilder.toString:()Ljava/lang/String;
   #99 = Utf8               testPair1
  #100 = Utf8               scala/Predef$
  #101 = Class              #100          // scala/Predef$
  #102 = Utf8               Lscala/Predef$;
  #103 = NameAndType        #14:#102      // MODULE$:Lscala/Predef$;
  #104 = Fieldref           #101.#103     // scala/Predef$.MODULE$:Lscala/Predef$;
  #105 = Integer            14
  #106 = Utf8               Key:
  #107 = String             #106          // Key:
  #108 = NameAndType        #8:#65        // intRefPair:()LbcGen/Classes/Pair;
  #109 = Methodref          #2.#108       // bcGen/Classes/testPair$.intRefPair:()LbcGen/Classes/Pair;
  #110 = Utf8               k
  #111 = NameAndType        #110:#59      // k:()Ljava/lang/Object;
  #112 = Methodref          #26.#111      // bcGen/Classes/Pair.k:()Ljava/lang/Object;
  #113 = Utf8               v
  #114 = NameAndType        #113:#59      // v:()Ljava/lang/Object;
  #115 = Methodref          #26.#114      // bcGen/Classes/Pair.v:()Ljava/lang/Object;
  #116 = Utf8               println
  #117 = Utf8               (Ljava/lang/Object;)V
  #118 = NameAndType        #116:#117     // println:(Ljava/lang/Object;)V
  #119 = Methodref          #101.#118     // scala/Predef$.println:(Ljava/lang/Object;)V
  #120 = Utf8               testPair5
  #121 = NameAndType        #68:#69       // passGenericPair:(LbcGen/Classes/Pair;)Ljava/lang/String;
  #122 = Methodref          #2.#121       // bcGen/Classes/testPair$.passGenericPair:(LbcGen/Classes/Pair;)Ljava/lang/String;
  #123 = Utf8               Ljava/lang/String;
  #124 = Utf8               Signature
  #125 = Utf8               Code
  #126 = Utf8               LineNumberTable
  #127 = Utf8               LocalVariableTable
  #128 = Utf8               InstructionTypeArguments
  #129 = Utf8               MethodParameters
  #130 = Utf8               InvokeReturnType
  #131 = Utf8               MethodTypeParameterCount
  #132 = Utf8               SourceFile
  #133 = Utf8               Scala
{
  private static final bcGen.Classes.Pair<java.lang.Object, java.lang.String> intRefPair;
    descriptor: LbcGen/Classes/Pair;
    flags: (0x001a) ACC_PRIVATE, ACC_STATIC, ACC_FINAL
    Signature: #10                          // LbcGen/Classes/Pair<Ljava/lang/Object;Ljava/lang/String;>;

  private static final bcGen.Classes.Pair<java.lang.Object, java.lang.Object> doubleLongPair;
    descriptor: LbcGen/Classes/Pair;
    flags: (0x001a) ACC_PRIVATE, ACC_STATIC, ACC_FINAL
    Signature: #12                          // LbcGen/Classes/Pair<Ljava/lang/Object;Ljava/lang/Object;>;

  private static final bcGen.Classes.Pair<java.lang.Object, java.lang.Object> anyAnyPair;
    descriptor: LbcGen/Classes/Pair;
    flags: (0x001a) ACC_PRIVATE, ACC_STATIC, ACC_FINAL
    Signature: #12                          // LbcGen/Classes/Pair<Ljava/lang/Object;Ljava/lang/Object;>;

  public static final bcGen.Classes.testPair$ MODULE$;
    descriptor: LbcGen/Classes/testPair$;
    flags: (0x0019) ACC_PUBLIC, ACC_STATIC, ACC_FINAL

  private bcGen.Classes.testPair$();
    descriptor: ()V
    flags: (0x0002) ACC_PRIVATE
    Code:
      stack=1, locals=1, args_size=1
         0: aload_0
         1: invokespecial #19                 // Method java/lang/Object."<init>":()V
         4: return
      LineNumberTable:
        line 14: 0
      LocalVariableTable:
        Start  Length  Slot  Name   Signature
            0       5     0  this   LbcGen/Classes/testPair$;

  public static {};
    descriptor: ()V
    flags: (0x0009) ACC_PUBLIC, ACC_STATIC
    Code:
      stack=5, locals=0, args_size=0
         0: new           #2                  // class bcGen/Classes/testPair$
         3: dup
         4: invokespecial #22                 // Method "<init>":()V
         7: putstatic     #24                 // Field MODULE$:LbcGen/Classes/testPair$;
        10: new           #26                 // class bcGen/Classes/Pair
        13: dup
        14: iconst_1
        15: invokestatic  #32                 // Method scala/runtime/BoxesRunTime.boxToInteger:(I)Ljava/lang/Integer;
        18: ldc           #34                 // String one
        20: invokespecial #37                 // Method bcGen/Classes/Pair."<init>":(Ljava/lang/Object;Ljava/lang/Object;)V
        23: putstatic     #39                 // Field intRefPair:LbcGen/Classes/Pair;
        26: new           #26                 // class bcGen/Classes/Pair
        29: dup
        30: ldc2_w        #40                 // double 3.14d
        33: invokestatic  #45                 // Method scala/runtime/BoxesRunTime.boxToDouble:(D)Ljava/lang/Double;
        36: ldc2_w        #46                 // long 42l
        39: invokestatic  #51                 // Method scala/runtime/BoxesRunTime.boxToLong:(J)Ljava/lang/Long;
        42: invokespecial #37                 // Method bcGen/Classes/Pair."<init>":(Ljava/lang/Object;Ljava/lang/Object;)V
        45: putstatic     #53                 // Field doubleLongPair:LbcGen/Classes/Pair;
        48: new           #26                 // class bcGen/Classes/Pair
        51: dup
        52: ldc           #55                 // String key
        54: sipush        232
        57: invokestatic  #32                 // Method scala/runtime/BoxesRunTime.boxToInteger:(I)Ljava/lang/Integer;
        60: invokespecial #37                 // Method bcGen/Classes/Pair."<init>":(Ljava/lang/Object;Ljava/lang/Object;)V
        63: putstatic     #57                 // Field anyAnyPair:LbcGen/Classes/Pair;
        66: return
      LineNumberTable:
        line 15: 0
        line 16: 26
        line 17: 48
      InstructionTypeArguments: length = 0x56 (unknown attribute)
       00 06 00 0A 00 02 49 00 00 00 00 4C 00 00 00 00
       00 14 00 02 49 00 00 00 00 4C 00 00 00 00 00 1A
       00 02 44 00 00 00 00 4A 00 00 00 00 00 2A 00 02
       44 00 00 00 00 4A 00 00 00 00 00 30 00 02 4C 00
       00 00 00 4C 00 00 00 00 00 3C 00 02 4C 00 00 00
       00 4C 00 00 00 00

  private java.lang.Object writeReplace();
    descriptor: ()Ljava/lang/Object;
    flags: (0x0002) ACC_PRIVATE
    Code:
      stack=3, locals=1, args_size=1
         0: new           #61                 // class scala/runtime/ModuleSerializationProxy
         3: dup
         4: ldc           #2                  // class bcGen/Classes/testPair$
         6: invokespecial #64                 // Method scala/runtime/ModuleSerializationProxy."<init>":(Ljava/lang/Class;)V
         9: areturn
      LineNumberTable:
        line 14: 0
      LocalVariableTable:
        Start  Length  Slot  Name   Signature
            0      10     0  this   LbcGen/Classes/testPair$;

  public bcGen.Classes.Pair<java.lang.Object, java.lang.String> intRefPair();
    descriptor: ()LbcGen/Classes/Pair;
    flags: (0x0001) ACC_PUBLIC
    Code:
      stack=1, locals=1, args_size=1
         0: getstatic     #39                 // Field intRefPair:LbcGen/Classes/Pair;
         3: areturn
      LineNumberTable:
        line 15: 0
      LocalVariableTable:
        Start  Length  Slot  Name   Signature
            0       4     0  this   LbcGen/Classes/testPair$;
    Signature: #66                          // ()LbcGen/Classes/Pair<Ljava/lang/Object;Ljava/lang/String;>;

  public bcGen.Classes.Pair<java.lang.Object, java.lang.Object> doubleLongPair();
    descriptor: ()LbcGen/Classes/Pair;
    flags: (0x0001) ACC_PUBLIC
    Code:
      stack=1, locals=1, args_size=1
         0: getstatic     #53                 // Field doubleLongPair:LbcGen/Classes/Pair;
         3: areturn
      LineNumberTable:
        line 16: 0
      LocalVariableTable:
        Start  Length  Slot  Name   Signature
            0       4     0  this   LbcGen/Classes/testPair$;
    Signature: #67                          // ()LbcGen/Classes/Pair<Ljava/lang/Object;Ljava/lang/Object;>;

  public bcGen.Classes.Pair<java.lang.Object, java.lang.Object> anyAnyPair();
    descriptor: ()LbcGen/Classes/Pair;
    flags: (0x0001) ACC_PUBLIC
    Code:
      stack=1, locals=1, args_size=1
         0: getstatic     #57                 // Field anyAnyPair:LbcGen/Classes/Pair;
         3: areturn
      LineNumberTable:
        line 17: 0
      LocalVariableTable:
        Start  Length  Slot  Name   Signature
            0       4     0  this   LbcGen/Classes/testPair$;
    Signature: #67                          // ()LbcGen/Classes/Pair<Ljava/lang/Object;Ljava/lang/Object;>;

  public <K extends java.lang.Object, V extends java.lang.Object> java.lang.String passGenericPair(bcGen.Classes.Pair<K, V>);
    descriptor: (LbcGen/Classes/Pair;)Ljava/lang/String;
    flags: (0x0001) ACC_PUBLIC
    Code:
      stack=3, locals=2, args_size=2
         0: new           #73                 // class java/lang/StringBuilder
         3: dup
         4: ldc           #74                 // int 29
         6: invokespecial #77                 // Method java/lang/StringBuilder."<init>":(I)V
         9: ldc           #79                 // String Generic Pair - Key:
        11: invokevirtual #83                 // Method java/lang/StringBuilder.append:(Ljava/lang/String;)Ljava/lang/StringBuilder;
        14: aload_1
        15: invokevirtual #86                 // Method bcGen/Classes/Pair.getKey:()Ljava/lang/Object;
        18: invokevirtual #89                 // Method java/lang/StringBuilder.append:(Ljava/lang/Object;)Ljava/lang/StringBuilder;
        21: ldc           #91                 // String , Value:
        23: invokevirtual #83                 // Method java/lang/StringBuilder.append:(Ljava/lang/String;)Ljava/lang/StringBuilder;
        26: aload_1
        27: invokevirtual #94                 // Method bcGen/Classes/Pair.getValue:()Ljava/lang/Object;
        30: invokevirtual #89                 // Method java/lang/StringBuilder.append:(Ljava/lang/Object;)Ljava/lang/StringBuilder;
        33: invokevirtual #98                 // Method java/lang/StringBuilder.toString:()Ljava/lang/String;
        36: areturn
      LineNumberTable:
        line 20: 0
      LocalVariableTable:
        Start  Length  Slot  Name   Signature
            0      37     0  this   LbcGen/Classes/testPair$;
            0      37     1  pair   LbcGen/Classes/Pair;
    Signature: #70                          // <K:Ljava/lang/Object;V:Ljava/lang/Object;>(LbcGen/Classes/Pair<TK;TV;>;)Ljava/lang/String;
    MethodParameters:
      Name                           Flags
      pair                           final
      InvokeReturnType: length = 0x10 (unknown attribute)
       00 02 00 0F 4D 00 00 00 00 00 1B 4D 00 00 00 01

      MethodTypeParameterCount: length = 0x2 (unknown attribute)
       00 02

  public void testPair1();
    descriptor: ()V
    flags: (0x0001) ACC_PUBLIC
    Code:
      stack=4, locals=1, args_size=1
         0: getstatic     #104                // Field scala/Predef$.MODULE$:Lscala/Predef$;
         3: new           #73                 // class java/lang/StringBuilder
         6: dup
         7: ldc           #105                // int 14
         9: invokespecial #77                 // Method java/lang/StringBuilder."<init>":(I)V
        12: ldc           #107                // String Key:
        14: invokevirtual #83                 // Method java/lang/StringBuilder.append:(Ljava/lang/String;)Ljava/lang/StringBuilder;
        17: aload_0
        18: invokevirtual #109                // Method intRefPair:()LbcGen/Classes/Pair;
        21: invokevirtual #112                // Method bcGen/Classes/Pair.k:()Ljava/lang/Object;
        24: invokevirtual #89                 // Method java/lang/StringBuilder.append:(Ljava/lang/Object;)Ljava/lang/StringBuilder;
        27: ldc           #91                 // String , Value:
        29: invokevirtual #83                 // Method java/lang/StringBuilder.append:(Ljava/lang/String;)Ljava/lang/StringBuilder;
        32: aload_0
        33: invokevirtual #109                // Method intRefPair:()LbcGen/Classes/Pair;
        36: invokevirtual #115                // Method bcGen/Classes/Pair.v:()Ljava/lang/Object;
        39: invokevirtual #89                 // Method java/lang/StringBuilder.append:(Ljava/lang/Object;)Ljava/lang/StringBuilder;
        42: invokevirtual #98                 // Method java/lang/StringBuilder.toString:()Ljava/lang/String;
        45: invokevirtual #119                // Method scala/Predef$.println:(Ljava/lang/Object;)V
        48: return
      LineNumberTable:
        line 24: 0
      LocalVariableTable:
        Start  Length  Slot  Name   Signature
            0      49     0  this   LbcGen/Classes/testPair$;

  public void testPair5();
    descriptor: ()V
    flags: (0x0001) ACC_PUBLIC
    Code:
      stack=2, locals=2, args_size=1
         0: aload_0
         1: aload_0
         2: invokevirtual #109                // Method intRefPair:()LbcGen/Classes/Pair;
         5: invokevirtual #122                // Method passGenericPair:(LbcGen/Classes/Pair;)Ljava/lang/String;
         8: astore_1
         9: getstatic     #104                // Field scala/Predef$.MODULE$:Lscala/Predef$;
        12: aload_1
        13: invokevirtual #119                // Method scala/Predef$.println:(Ljava/lang/Object;)V
        16: return
      LineNumberTable:
        line 28: 0
        line 29: 9
      LocalVariableTable:
        Start  Length  Slot  Name   Signature
            9       8     1     v   Ljava/lang/String;
            0      17     0  this   LbcGen/Classes/testPair$;
      InstructionTypeArguments: length = 0x10 (unknown attribute)
       00 01 00 05 00 02 49 00 00 00 00 4C 00 00 00 00

}
SourceFile: "Pair.scala"
  Scala: length = 0x0 (unknown attribute)

