Classfile /u0/j523xu/scala3/out/bcGen/Methods/MethodTestCases$.class
  Last modified Oct 16, 2025; size 2444 bytes
  SHA-256 checksum dcd65dfd9861908b8e6af502f089c329d1ba849571c82b2765af5aaccf6534af
  Compiled from "MethodTestCases.scala"
public final class bcGen.Methods.MethodTestCases$ implements java.io.Serializable
  minor version: 0
  major version: 52
  flags: (0x0031) ACC_PUBLIC, ACC_FINAL, ACC_SUPER
  this_class: #2                          // bcGen/Methods/MethodTestCases$
  super_class: #4                         // java/lang/Object
  interfaces: 1, fields: 2, methods: 6, attributes: 2
Constant pool:
    #1 = Utf8               bcGen/Methods/MethodTestCases$
    #2 = Class              #1            // bcGen/Methods/MethodTestCases$
    #3 = Utf8               java/lang/Object
    #4 = Class              #3            // java/lang/Object
    #5 = Utf8               java/io/Serializable
    #6 = Class              #5            // java/io/Serializable
    #7 = Utf8               MethodTestCases.scala
    #8 = Utf8               rng
    #9 = Utf8               Lscala/util/Random;
   #10 = Utf8               MODULE$
   #11 = Utf8               LbcGen/Methods/MethodTestCases$;
   #12 = Utf8               <init>
   #13 = Utf8               ()V
   #14 = NameAndType        #12:#13       // "<init>":()V
   #15 = Methodref          #4.#14        // java/lang/Object."<init>":()V
   #16 = Utf8               this
   #17 = Utf8               <clinit>
   #18 = Methodref          #2.#14        // bcGen/Methods/MethodTestCases$."<init>":()V
   #19 = NameAndType        #10:#11       // MODULE$:LbcGen/Methods/MethodTestCases$;
   #20 = Fieldref           #2.#19        // bcGen/Methods/MethodTestCases$.MODULE$:LbcGen/Methods/MethodTestCases$;
   #21 = Utf8               scala/util/Random
   #22 = Class              #21           // scala/util/Random
   #23 = Utf8               (I)V
   #24 = NameAndType        #12:#23       // "<init>":(I)V
   #25 = Methodref          #22.#24       // scala/util/Random."<init>":(I)V
   #26 = NameAndType        #8:#9         // rng:Lscala/util/Random;
   #27 = Fieldref           #2.#26        // bcGen/Methods/MethodTestCases$.rng:Lscala/util/Random;
   #28 = Utf8               writeReplace
   #29 = Utf8               ()Ljava/lang/Object;
   #30 = Utf8               scala/runtime/ModuleSerializationProxy
   #31 = Class              #30           // scala/runtime/ModuleSerializationProxy
   #32 = Utf8               (Ljava/lang/Class;)V
   #33 = NameAndType        #12:#32       // "<init>":(Ljava/lang/Class;)V
   #34 = Methodref          #31.#33       // scala/runtime/ModuleSerializationProxy."<init>":(Ljava/lang/Class;)V
   #35 = Utf8               ()Lscala/util/Random;
   #36 = Utf8               runIdentityInt
   #37 = Integer            1000000
   #38 = Utf8               bcGen/Methods/MethodTestLib$
   #39 = Class              #38           // bcGen/Methods/MethodTestLib$
   #40 = Utf8               LbcGen/Methods/MethodTestLib$;
   #41 = NameAndType        #10:#40       // MODULE$:LbcGen/Methods/MethodTestLib$;
   #42 = Fieldref           #39.#41       // bcGen/Methods/MethodTestLib$.MODULE$:LbcGen/Methods/MethodTestLib$;
   #43 = Utf8               scala/runtime/BoxesRunTime
   #44 = Class              #43           // scala/runtime/BoxesRunTime
   #45 = Utf8               boxToInteger
   #46 = Utf8               (I)Ljava/lang/Integer;
   #47 = NameAndType        #45:#46       // boxToInteger:(I)Ljava/lang/Integer;
   #48 = Methodref          #44.#47       // scala/runtime/BoxesRunTime.boxToInteger:(I)Ljava/lang/Integer;
   #49 = Utf8               identity
   #50 = Utf8               (Ljava/lang/Object;)Ljava/lang/Object;
   #51 = NameAndType        #49:#50       // identity:(Ljava/lang/Object;)Ljava/lang/Object;
   #52 = Methodref          #39.#51       // bcGen/Methods/MethodTestLib$.identity:(Ljava/lang/Object;)Ljava/lang/Object;
   #53 = Utf8               unboxToInt
   #54 = Utf8               (Ljava/lang/Object;)I
   #55 = NameAndType        #53:#54       // unboxToInt:(Ljava/lang/Object;)I
   #56 = Methodref          #44.#55       // scala/runtime/BoxesRunTime.unboxToInt:(Ljava/lang/Object;)I
   #57 = Utf8               scala/Predef$
   #58 = Class              #57           // scala/Predef$
   #59 = Utf8               Lscala/Predef$;
   #60 = NameAndType        #10:#59       // MODULE$:Lscala/Predef$;
   #61 = Fieldref           #58.#60       // scala/Predef$.MODULE$:Lscala/Predef$;
   #62 = Utf8               java/lang/StringBuilder
   #63 = Class              #62           // java/lang/StringBuilder
   #64 = Integer            26
   #65 = Methodref          #63.#24       // java/lang/StringBuilder."<init>":(I)V
   #66 = Utf8               Sum of
   #67 = String             #66           // Sum of
   #68 = Utf8               append
   #69 = Utf8               (Ljava/lang/String;)Ljava/lang/StringBuilder;
   #70 = NameAndType        #68:#69       // append:(Ljava/lang/String;)Ljava/lang/StringBuilder;
   #71 = Methodref          #63.#70       // java/lang/StringBuilder.append:(Ljava/lang/String;)Ljava/lang/StringBuilder;
   #72 = Utf8               (I)Ljava/lang/StringBuilder;
   #73 = NameAndType        #68:#72       // append:(I)Ljava/lang/StringBuilder;
   #74 = Methodref          #63.#73       // java/lang/StringBuilder.append:(I)Ljava/lang/StringBuilder;
   #75 = Utf8                identities of
   #76 = String             #75           //  identities of
   #77 = Utf8                is
   #78 = String             #77           //  is
   #79 = Utf8               toString
   #80 = Utf8               ()Ljava/lang/String;
   #81 = NameAndType        #79:#80       // toString:()Ljava/lang/String;
   #82 = Methodref          #63.#81       // java/lang/StringBuilder.toString:()Ljava/lang/String;
   #83 = Utf8               println
   #84 = Utf8               (Ljava/lang/Object;)V
   #85 = NameAndType        #83:#84       // println:(Ljava/lang/Object;)V
   #86 = Methodref          #58.#85       // scala/Predef$.println:(Ljava/lang/Object;)V
   #87 = Utf8               repeat
   #88 = Utf8               I
   #89 = Utf8               input
   #90 = Utf8               sum
   #91 = Utf8               i
   #92 = Utf8               runFirstMixed
   #93 = NameAndType        #8:#35        // rng:()Lscala/util/Random;
   #94 = Methodref          #2.#93        // bcGen/Methods/MethodTestCases$.rng:()Lscala/util/Random;
   #95 = Utf8               nextInt
   #96 = Utf8               (I)I
   #97 = NameAndType        #95:#96       // nextInt:(I)I
   #98 = Methodref          #22.#97       // scala/util/Random.nextInt:(I)I
   #99 = Utf8               boxToDouble
  #100 = Utf8               (D)Ljava/lang/Double;
  #101 = NameAndType        #99:#100      // boxToDouble:(D)Ljava/lang/Double;
  #102 = Methodref          #44.#101      // scala/runtime/BoxesRunTime.boxToDouble:(D)Ljava/lang/Double;
  #103 = Utf8               first
  #104 = Utf8               (Ljava/lang/Object;Ljava/lang/Object;)Ljava/lang/Object;
  #105 = NameAndType        #103:#104     // first:(Ljava/lang/Object;Ljava/lang/Object;)Ljava/lang/Object;
  #106 = Methodref          #39.#105      // bcGen/Methods/MethodTestLib$.first:(Ljava/lang/Object;Ljava/lang/Object;)Ljava/lang/Object;
  #107 = Utf8               unboxToDouble
  #108 = Utf8               (Ljava/lang/Object;)D
  #109 = NameAndType        #107:#108     // unboxToDouble:(Ljava/lang/Object;)D
  #110 = Methodref          #44.#109      // scala/runtime/BoxesRunTime.unboxToDouble:(Ljava/lang/Object;)D
  #111 = Integer            33
  #112 = Utf8                firsts is int:
  #113 = String             #112          //  firsts is int:
  #114 = Utf8               , double:
  #115 = String             #114          // , double:
  #116 = Utf8               (D)Ljava/lang/StringBuilder;
  #117 = NameAndType        #68:#116      // append:(D)Ljava/lang/StringBuilder;
  #118 = Methodref          #63.#117      // java/lang/StringBuilder.append:(D)Ljava/lang/StringBuilder;
  #119 = Utf8               n
  #120 = Utf8               sumInt
  #121 = Utf8               sumDouble
  #122 = Utf8               D
  #123 = Utf8               Code
  #124 = Utf8               LineNumberTable
  #125 = Utf8               LocalVariableTable
  #126 = Utf8               Signature
  #127 = Utf8               StackMapTable
  #128 = Utf8               InstructionTypeArguments
  #129 = Utf8               SourceFile
  #130 = Utf8               Scala
{
  private static final scala.util.Random rng;
    descriptor: Lscala/util/Random;
    flags: (0x001a) ACC_PRIVATE, ACC_STATIC, ACC_FINAL

  public static final bcGen.Methods.MethodTestCases$ MODULE$;
    descriptor: LbcGen/Methods/MethodTestCases$;
    flags: (0x0019) ACC_PUBLIC, ACC_STATIC, ACC_FINAL

  private bcGen.Methods.MethodTestCases$();
    descriptor: ()V
    flags: (0x0002) ACC_PRIVATE
    Code:
      stack=1, locals=1, args_size=1
         0: aload_0
         1: invokespecial #15                 // Method java/lang/Object."<init>":()V
         4: return
      LineNumberTable:
        line 3: 0
      LocalVariableTable:
        Start  Length  Slot  Name   Signature
            0       5     0  this   LbcGen/Methods/MethodTestCases$;

  public static {};
    descriptor: ()V
    flags: (0x0009) ACC_PUBLIC, ACC_STATIC
    Code:
      stack=3, locals=0, args_size=0
         0: new           #2                  // class bcGen/Methods/MethodTestCases$
         3: dup
         4: invokespecial #18                 // Method "<init>":()V
         7: putstatic     #20                 // Field MODULE$:LbcGen/Methods/MethodTestCases$;
        10: new           #22                 // class scala/util/Random
        13: dup
        14: sipush        1234
        17: invokespecial #25                 // Method scala/util/Random."<init>":(I)V
        20: putstatic     #27                 // Field rng:Lscala/util/Random;
        23: return
      LineNumberTable:
        line 4: 0

  private java.lang.Object writeReplace();
    descriptor: ()Ljava/lang/Object;
    flags: (0x0002) ACC_PRIVATE
    Code:
      stack=3, locals=1, args_size=1
         0: new           #31                 // class scala/runtime/ModuleSerializationProxy
         3: dup
         4: ldc           #2                  // class bcGen/Methods/MethodTestCases$
         6: invokespecial #34                 // Method scala/runtime/ModuleSerializationProxy."<init>":(Ljava/lang/Class;)V
         9: areturn
      LineNumberTable:
        line 3: 0
      LocalVariableTable:
        Start  Length  Slot  Name   Signature
            0      10     0  this   LbcGen/Methods/MethodTestCases$;

  public scala.util.Random rng();
    descriptor: ()Lscala/util/Random;
    flags: (0x0001) ACC_PUBLIC
    Code:
      stack=1, locals=1, args_size=1
         0: getstatic     #27                 // Field rng:Lscala/util/Random;
         3: areturn
      LineNumberTable:
        line 4: 0
      LocalVariableTable:
        Start  Length  Slot  Name   Signature
            0       4     0  this   LbcGen/Methods/MethodTestCases$;
    Signature: #35                          // ()Lscala/util/Random;

  public void runIdentityInt();
    descriptor: ()V
    flags: (0x0001) ACC_PUBLIC
    Code:
      stack=4, locals=5, args_size=1
         0: ldc           #37                 // int 1000000
         2: istore_1
         3: bipush        42
         5: istore_2
         6: iconst_0
         7: istore_3
         8: iconst_0
         9: istore        4
        11: iload         4
        13: iload_1
        14: if_icmpge     39
        17: iload_3
        18: getstatic     #42                 // Field bcGen/Methods/MethodTestLib$.MODULE$:LbcGen/Methods/MethodTestLib$;
        21: iload_2
        22: invokestatic  #48                 // Method scala/runtime/BoxesRunTime.boxToInteger:(I)Ljava/lang/Integer;
        25: invokevirtual #52                 // Method bcGen/Methods/MethodTestLib$.identity:(Ljava/lang/Object;)Ljava/lang/Object;
        28: invokestatic  #56                 // Method scala/runtime/BoxesRunTime.unboxToInt:(Ljava/lang/Object;)I
        31: iadd
        32: istore_3
        33: iinc          4, 1
        36: goto          11
        39: getstatic     #61                 // Field scala/Predef$.MODULE$:Lscala/Predef$;
        42: new           #63                 // class java/lang/StringBuilder
        45: dup
        46: ldc           #64                 // int 26
        48: invokespecial #65                 // Method java/lang/StringBuilder."<init>":(I)V
        51: ldc           #67                 // String Sum of
        53: invokevirtual #71                 // Method java/lang/StringBuilder.append:(Ljava/lang/String;)Ljava/lang/StringBuilder;
        56: iload_1
        57: invokevirtual #74                 // Method java/lang/StringBuilder.append:(I)Ljava/lang/StringBuilder;
        60: ldc           #76                 // String  identities of
        62: invokevirtual #71                 // Method java/lang/StringBuilder.append:(Ljava/lang/String;)Ljava/lang/StringBuilder;
        65: iload_2
        66: invokevirtual #74                 // Method java/lang/StringBuilder.append:(I)Ljava/lang/StringBuilder;
        69: ldc           #78                 // String  is
        71: invokevirtual #71                 // Method java/lang/StringBuilder.append:(Ljava/lang/String;)Ljava/lang/StringBuilder;
        74: iload_3
        75: invokevirtual #74                 // Method java/lang/StringBuilder.append:(I)Ljava/lang/StringBuilder;
        78: invokevirtual #82                 // Method java/lang/StringBuilder.toString:()Ljava/lang/String;
        81: invokevirtual #86                 // Method scala/Predef$.println:(Ljava/lang/Object;)V
        84: return
      StackMapTable: number_of_entries = 2
        frame_type = 255 /* full_frame */
          offset_delta = 11
          locals = [ class bcGen/Methods/MethodTestCases$, int, int, int, int ]
          stack = []
        frame_type = 27 /* same */
      LineNumberTable:
        line 8: 0
        line 9: 3
        line 10: 6
        line 11: 8
        line 12: 11
        line 13: 17
        line 14: 33
        line 16: 39
      LocalVariableTable:
        Start  Length  Slot  Name   Signature
            3      82     1 repeat   I
            6      79     2 input   I
            8      77     3   sum   I
           11      74     4     i   I
            0      85     0  this   LbcGen/Methods/MethodTestCases$;
      InstructionTypeArguments: length = 0xB (unknown attribute)
       00 01 00 19 00 01 49 00 00 00 00

  public void runFirstMixed();
    descriptor: ()V
    flags: (0x0001) ACC_PUBLIC
    Code:
      stack=5, locals=7, args_size=1
         0: sipush        10000
         3: istore_1
         4: iconst_0
         5: istore_2
         6: iconst_0
         7: istore_3
         8: dconst_0
         9: dstore        4
        11: iload_2
        12: iload_1
        13: if_icmpge     85
        16: aload_0
        17: invokevirtual #94                 // Method rng:()Lscala/util/Random;
        20: iconst_2
        21: invokevirtual #98                 // Method scala/util/Random.nextInt:(I)I
        24: istore        6
        26: iload         6
        28: iconst_0
        29: if_icmpne     56
        32: iload_3
        33: getstatic     #42                 // Field bcGen/Methods/MethodTestLib$.MODULE$:LbcGen/Methods/MethodTestLib$;
        36: iload_2
        37: invokestatic  #48                 // Method scala/runtime/BoxesRunTime.boxToInteger:(I)Ljava/lang/Integer;
        40: iload_2
        41: i2d
        42: invokestatic  #102                // Method scala/runtime/BoxesRunTime.boxToDouble:(D)Ljava/lang/Double;
        45: invokevirtual #106                // Method bcGen/Methods/MethodTestLib$.first:(Ljava/lang/Object;Ljava/lang/Object;)Ljava/lang/Object;
        48: invokestatic  #56                 // Method scala/runtime/BoxesRunTime.unboxToInt:(Ljava/lang/Object;)I
        51: iadd
        52: istore_3
        53: goto          79
        56: dload         4
        58: getstatic     #42                 // Field bcGen/Methods/MethodTestLib$.MODULE$:LbcGen/Methods/MethodTestLib$;
        61: iload_2
        62: i2d
        63: invokestatic  #102                // Method scala/runtime/BoxesRunTime.boxToDouble:(D)Ljava/lang/Double;
        66: iload_2
        67: invokestatic  #48                 // Method scala/runtime/BoxesRunTime.boxToInteger:(I)Ljava/lang/Integer;
        70: invokevirtual #106                // Method bcGen/Methods/MethodTestLib$.first:(Ljava/lang/Object;Ljava/lang/Object;)Ljava/lang/Object;
        73: invokestatic  #110                // Method scala/runtime/BoxesRunTime.unboxToDouble:(Ljava/lang/Object;)D
        76: dadd
        77: dstore        4
        79: iinc          2, 1
        82: goto          11
        85: getstatic     #61                 // Field scala/Predef$.MODULE$:Lscala/Predef$;
        88: new           #63                 // class java/lang/StringBuilder
        91: dup
        92: ldc           #111                // int 33
        94: invokespecial #65                 // Method java/lang/StringBuilder."<init>":(I)V
        97: ldc           #67                 // String Sum of
        99: invokevirtual #71                 // Method java/lang/StringBuilder.append:(Ljava/lang/String;)Ljava/lang/StringBuilder;
       102: iload_1
       103: invokevirtual #74                 // Method java/lang/StringBuilder.append:(I)Ljava/lang/StringBuilder;
       106: ldc           #113                // String  firsts is int:
       108: invokevirtual #71                 // Method java/lang/StringBuilder.append:(Ljava/lang/String;)Ljava/lang/StringBuilder;
       111: iload_3
       112: invokevirtual #74                 // Method java/lang/StringBuilder.append:(I)Ljava/lang/StringBuilder;
       115: ldc           #115                // String , double:
       117: invokevirtual #71                 // Method java/lang/StringBuilder.append:(Ljava/lang/String;)Ljava/lang/StringBuilder;
       120: dload         4
       122: invokevirtual #118                // Method java/lang/StringBuilder.append:(D)Ljava/lang/StringBuilder;
       125: invokevirtual #82                 // Method java/lang/StringBuilder.toString:()Ljava/lang/String;
       128: invokevirtual #86                 // Method scala/Predef$.println:(Ljava/lang/Object;)V
       131: return
      StackMapTable: number_of_entries = 4
        frame_type = 255 /* full_frame */
          offset_delta = 11
          locals = [ class bcGen/Methods/MethodTestCases$, int, int, int, double ]
          stack = []
        frame_type = 252 /* append */
          offset_delta = 44
          locals = [ int ]
        frame_type = 22 /* same */
        frame_type = 250 /* chop */
          offset_delta = 5
      LineNumberTable:
        line 20: 0
        line 21: 4
        line 22: 6
        line 23: 8
        line 24: 11
        line 25: 16
        line 26: 26
        line 27: 32
        line 29: 56
        line 31: 79
        line 33: 85
      LocalVariableTable:
        Start  Length  Slot  Name   Signature
           26      59     6     n   I
            4     128     1 repeat   I
            6     126     2     i   I
            8     124     3 sumInt   I
           11     121     4 sumDouble   D
            0     132     0  this   LbcGen/Methods/MethodTestCases$;
      InstructionTypeArguments: length = 0x1E (unknown attribute)
       00 02 00 2D 00 02 49 00 00 00 00 44 00 00 00 00
       00 46 00 02 44 00 00 00 00 49 00 00 00 00
}
SourceFile: "MethodTestCases.scala"
  Scala: length = 0x0 (unknown attribute)

