Classfile /u0/j523xu/scala3/out/bcGen/Methods/MethodTestLib$.class
  Last modified Oct 16, 2025; size 1216 bytes
  SHA-256 checksum dc115da93d2d138df61ac8744dbc01be2aa73050351e092314559b52ca673f2b
  Compiled from "MethodTestLib.scala"
public final class bcGen.Methods.MethodTestLib$ implements java.io.Serializable
  minor version: 0
  major version: 52
  flags: (0x0031) ACC_PUBLIC, ACC_FINAL, ACC_SUPER
  this_class: #2                          // bcGen/Methods/MethodTestLib$
  super_class: #4                         // java/lang/Object
  interfaces: 1, fields: 1, methods: 5, attributes: 2
Constant pool:
   #1 = Utf8               bcGen/Methods/MethodTestLib$
   #2 = Class              #1             // bcGen/Methods/MethodTestLib$
   #3 = Utf8               java/lang/Object
   #4 = Class              #3             // java/lang/Object
   #5 = Utf8               java/io/Serializable
   #6 = Class              #5             // java/io/Serializable
   #7 = Utf8               MethodTestLib.scala
   #8 = Utf8               MODULE$
   #9 = Utf8               LbcGen/Methods/MethodTestLib$;
  #10 = Utf8               <init>
  #11 = Utf8               ()V
  #12 = NameAndType        #10:#11        // "<init>":()V
  #13 = Methodref          #4.#12         // java/lang/Object."<init>":()V
  #14 = Utf8               this
  #15 = Utf8               <clinit>
  #16 = Methodref          #2.#12         // bcGen/Methods/MethodTestLib$."<init>":()V
  #17 = NameAndType        #8:#9          // MODULE$:LbcGen/Methods/MethodTestLib$;
  #18 = Fieldref           #2.#17         // bcGen/Methods/MethodTestLib$.MODULE$:LbcGen/Methods/MethodTestLib$;
  #19 = Utf8               writeReplace
  #20 = Utf8               ()Ljava/lang/Object;
  #21 = Utf8               scala/runtime/ModuleSerializationProxy
  #22 = Class              #21            // scala/runtime/ModuleSerializationProxy
  #23 = Utf8               (Ljava/lang/Class;)V
  #24 = NameAndType        #10:#23        // "<init>":(Ljava/lang/Class;)V
  #25 = Methodref          #22.#24        // scala/runtime/ModuleSerializationProxy."<init>":(Ljava/lang/Class;)V
  #26 = Utf8               identity
  #27 = Utf8               (Ljava/lang/Object;)Ljava/lang/Object;
  #28 = Utf8               <T:Ljava/lang/Object;>(TT;)TT;
  #29 = Utf8               value
  #30 = Utf8               Ljava/lang/Object;
  #31 = Utf8               first
  #32 = Utf8               (Ljava/lang/Object;Ljava/lang/Object;)Ljava/lang/Object;
  #33 = Utf8               <U:Ljava/lang/Object;V:Ljava/lang/Object;>(TU;TV;)TU;
  #34 = Utf8               fst
  #35 = Utf8               snd
  #36 = Utf8               Code
  #37 = Utf8               LineNumberTable
  #38 = Utf8               LocalVariableTable
  #39 = Utf8               Signature
  #40 = Utf8               MethodParameters
  #41 = Utf8               MethodReturnType
  #42 = Utf8               MethodParameterType
  #43 = Utf8               MethodTypeParameterCount
  #44 = Utf8               SourceFile
  #45 = Utf8               Scala
{
  public static final bcGen.Methods.MethodTestLib$ MODULE$;
    descriptor: LbcGen/Methods/MethodTestLib$;
    flags: (0x0019) ACC_PUBLIC, ACC_STATIC, ACC_FINAL

  private bcGen.Methods.MethodTestLib$();
    descriptor: ()V
    flags: (0x0002) ACC_PRIVATE
    Code:
      stack=1, locals=1, args_size=1
         0: aload_0
         1: invokespecial #13                 // Method java/lang/Object."<init>":()V
         4: return
      LineNumberTable:
        line 3: 0
      LocalVariableTable:
        Start  Length  Slot  Name   Signature
            0       5     0  this   LbcGen/Methods/MethodTestLib$;

  public static {};
    descriptor: ()V
    flags: (0x0009) ACC_PUBLIC, ACC_STATIC
    Code:
      stack=2, locals=0, args_size=0
         0: new           #2                  // class bcGen/Methods/MethodTestLib$
         3: dup
         4: invokespecial #16                 // Method "<init>":()V
         7: putstatic     #18                 // Field MODULE$:LbcGen/Methods/MethodTestLib$;
        10: return
      LineNumberTable:
        line 5: 0

  private java.lang.Object writeReplace();
    descriptor: ()Ljava/lang/Object;
    flags: (0x0002) ACC_PRIVATE
    Code:
      stack=3, locals=1, args_size=1
         0: new           #22                 // class scala/runtime/ModuleSerializationProxy
         3: dup
         4: ldc           #2                  // class bcGen/Methods/MethodTestLib$
         6: invokespecial #25                 // Method scala/runtime/ModuleSerializationProxy."<init>":(Ljava/lang/Class;)V
         9: areturn
      LineNumberTable:
        line 3: 0
      LocalVariableTable:
        Start  Length  Slot  Name   Signature
            0      10     0  this   LbcGen/Methods/MethodTestLib$;

  public <T extends java.lang.Object> T identity(T);
    descriptor: (Ljava/lang/Object;)Ljava/lang/Object;
    flags: (0x0001) ACC_PUBLIC
    Code:
      stack=1, locals=2, args_size=2
         0: aload_1
         1: areturn
      LineNumberTable:
        line 5: 0
      LocalVariableTable:
        Start  Length  Slot  Name   Signature
            0       2     0  this   LbcGen/Methods/MethodTestLib$;
            0       2     1 value   Ljava/lang/Object;
    Signature: #28                          // <T:Ljava/lang/Object;>(TT;)TT;
    MethodParameters:
      Name                           Flags
      value                          final
      MethodReturnType: length = 0x5 (unknown attribute)
       4D 00 00 00 00
      MethodParameterType: length = 0x7 (unknown attribute)
       00 01 4D 00 00 00 00
      MethodTypeParameterCount: length = 0x2 (unknown attribute)
       00 01

  public <U extends java.lang.Object, V extends java.lang.Object> U first(U, V);
    descriptor: (Ljava/lang/Object;Ljava/lang/Object;)Ljava/lang/Object;
    flags: (0x0001) ACC_PUBLIC
    Code:
      stack=1, locals=3, args_size=3
         0: aload_1
         1: areturn
      LineNumberTable:
        line 7: 0
      LocalVariableTable:
        Start  Length  Slot  Name   Signature
            0       2     0  this   LbcGen/Methods/MethodTestLib$;
            0       2     1   fst   Ljava/lang/Object;
            0       2     2   snd   Ljava/lang/Object;
    Signature: #33                          // <U:Ljava/lang/Object;V:Ljava/lang/Object;>(TU;TV;)TU;
    MethodParameters:
      Name                           Flags
      fst                            final
      snd                            final
      MethodReturnType: length = 0x5 (unknown attribute)
       4D 00 00 00 00
      MethodParameterType: length = 0xC (unknown attribute)
       00 02 4D 00 00 00 00 4D 00 00 00 01
      MethodTypeParameterCount: length = 0x2 (unknown attribute)
       00 02
}
SourceFile: "MethodTestLib.scala"
  Scala: length = 0x0 (unknown attribute)

