Classfile /u0/j523xu/scala3/out/bcGen/Arrays/ArrayTestLib$.class
  Last modified Oct 16, 2025; size 1684 bytes
  SHA-256 checksum 675b7961ddde1554ead7dc81eb0080dcc77009bfb313b8c5da4d25074c04864c
  Compiled from "ArrayTestLib.scala"
public final class bcGen.Arrays.ArrayTestLib$ implements java.io.Serializable
  minor version: 0
  major version: 52
  flags: (0x0031) ACC_PUBLIC, ACC_FINAL, ACC_SUPER
  this_class: #2                          // bcGen/Arrays/ArrayTestLib$
  super_class: #4                         // java/lang/Object
  interfaces: 1, fields: 1, methods: 5, attributes: 2
Constant pool:
   #1 = Utf8               bcGen/Arrays/ArrayTestLib$
   #2 = Class              #1             // bcGen/Arrays/ArrayTestLib$
   #3 = Utf8               java/lang/Object
   #4 = Class              #3             // java/lang/Object
   #5 = Utf8               java/io/Serializable
   #6 = Class              #5             // java/io/Serializable
   #7 = Utf8               ArrayTestLib.scala
   #8 = Utf8               MODULE$
   #9 = Utf8               LbcGen/Arrays/ArrayTestLib$;
  #10 = Utf8               <init>
  #11 = Utf8               ()V
  #12 = NameAndType        #10:#11        // "<init>":()V
  #13 = Methodref          #4.#12         // java/lang/Object."<init>":()V
  #14 = Utf8               this
  #15 = Utf8               <clinit>
  #16 = Methodref          #2.#12         // bcGen/Arrays/ArrayTestLib$."<init>":()V
  #17 = NameAndType        #8:#9          // MODULE$:LbcGen/Arrays/ArrayTestLib$;
  #18 = Fieldref           #2.#17         // bcGen/Arrays/ArrayTestLib$.MODULE$:LbcGen/Arrays/ArrayTestLib$;
  #19 = Utf8               writeReplace
  #20 = Utf8               ()Ljava/lang/Object;
  #21 = Utf8               scala/runtime/ModuleSerializationProxy
  #22 = Class              #21            // scala/runtime/ModuleSerializationProxy
  #23 = Utf8               (Ljava/lang/Class;)V
  #24 = NameAndType        #10:#23        // "<init>":(Ljava/lang/Class;)V
  #25 = Methodref          #22.#24        // scala/runtime/ModuleSerializationProxy."<init>":(Ljava/lang/Class;)V
  #26 = Utf8               copy
  #27 = Utf8               (Ljava/lang/Object;Ljava/lang/Object;)V
  #28 = Utf8               <T:Ljava/lang/Object;>(Ljava/lang/Object;Ljava/lang/Object;)V
  #29 = Utf8               src
  #30 = Utf8               dst
  #31 = Utf8               scala/runtime/ScalaRunTime$
  #32 = Class              #31            // scala/runtime/ScalaRunTime$
  #33 = Utf8               Lscala/runtime/ScalaRunTime$;
  #34 = NameAndType        #8:#33         // MODULE$:Lscala/runtime/ScalaRunTime$;
  #35 = Fieldref           #32.#34        // scala/runtime/ScalaRunTime$.MODULE$:Lscala/runtime/ScalaRunTime$;
  #36 = Utf8               array_length
  #37 = Utf8               (Ljava/lang/Object;)I
  #38 = NameAndType        #36:#37        // array_length:(Ljava/lang/Object;)I
  #39 = Methodref          #32.#38        // scala/runtime/ScalaRunTime$.array_length:(Ljava/lang/Object;)I
  #40 = Utf8               array_apply
  #41 = Utf8               (Ljava/lang/Object;I)Ljava/lang/Object;
  #42 = NameAndType        #40:#41        // array_apply:(Ljava/lang/Object;I)Ljava/lang/Object;
  #43 = Methodref          #32.#42        // scala/runtime/ScalaRunTime$.array_apply:(Ljava/lang/Object;I)Ljava/lang/Object;
  #44 = Utf8               array_update
  #45 = Utf8               (Ljava/lang/Object;ILjava/lang/Object;)V
  #46 = NameAndType        #44:#45        // array_update:(Ljava/lang/Object;ILjava/lang/Object;)V
  #47 = Methodref          #32.#46        // scala/runtime/ScalaRunTime$.array_update:(Ljava/lang/Object;ILjava/lang/Object;)V
  #48 = Utf8               idx
  #49 = Utf8               I
  #50 = Utf8               Ljava/lang/Object;
  #51 = Utf8               checksum
  #52 = Utf8               <T:Ljava/lang/Object;>(Ljava/lang/Object;)I
  #53 = Utf8               array
  #54 = Utf8               scala/runtime/Statics
  #55 = Class              #54            // scala/runtime/Statics
  #56 = Utf8               anyHash
  #57 = NameAndType        #56:#37        // anyHash:(Ljava/lang/Object;)I
  #58 = Methodref          #55.#57        // scala/runtime/Statics.anyHash:(Ljava/lang/Object;)I
  #59 = Utf8               sum
  #60 = Utf8               i
  #61 = Utf8               Code
  #62 = Utf8               LineNumberTable
  #63 = Utf8               LocalVariableTable
  #64 = Utf8               StackMapTable
  #65 = Utf8               Signature
  #66 = Utf8               MethodParameters
  #67 = Utf8               InvokeReturnType
  #68 = Utf8               MethodParameterType
  #69 = Utf8               MethodTypeParameterCount
  #70 = Utf8               SourceFile
  #71 = Utf8               Scala
{
  public static final bcGen.Arrays.ArrayTestLib$ MODULE$;
    descriptor: LbcGen/Arrays/ArrayTestLib$;
    flags: (0x0019) ACC_PUBLIC, ACC_STATIC, ACC_FINAL

  private bcGen.Arrays.ArrayTestLib$();
    descriptor: ()V
    flags: (0x0002) ACC_PRIVATE
    Code:
      stack=1, locals=1, args_size=1
         0: aload_0
         1: invokespecial #13                 // Method java/lang/Object."<init>":()V
         4: return
      LineNumberTable:
        line 3: 0
      LocalVariableTable:
        Start  Length  Slot  Name   Signature
            0       5     0  this   LbcGen/Arrays/ArrayTestLib$;

  public static {};
    descriptor: ()V
    flags: (0x0009) ACC_PUBLIC, ACC_STATIC
    Code:
      stack=2, locals=0, args_size=0
         0: new           #2                  // class bcGen/Arrays/ArrayTestLib$
         3: dup
         4: invokespecial #16                 // Method "<init>":()V
         7: putstatic     #18                 // Field MODULE$:LbcGen/Arrays/ArrayTestLib$;
        10: return
      LineNumberTable:
        line 4: 0

  private java.lang.Object writeReplace();
    descriptor: ()Ljava/lang/Object;
    flags: (0x0002) ACC_PRIVATE
    Code:
      stack=3, locals=1, args_size=1
         0: new           #22                 // class scala/runtime/ModuleSerializationProxy
         3: dup
         4: ldc           #2                  // class bcGen/Arrays/ArrayTestLib$
         6: invokespecial #25                 // Method scala/runtime/ModuleSerializationProxy."<init>":(Ljava/lang/Class;)V
         9: areturn
      LineNumberTable:
        line 3: 0
      LocalVariableTable:
        Start  Length  Slot  Name   Signature
            0      10     0  this   LbcGen/Arrays/ArrayTestLib$;

  public <T extends java.lang.Object> void copy(java.lang.Object, java.lang.Object);
    descriptor: (Ljava/lang/Object;Ljava/lang/Object;)V
    flags: (0x0001) ACC_PUBLIC
    Code:
      stack=6, locals=4, args_size=3
         0: iconst_0
         1: istore_3
         2: iload_3
         3: getstatic     #35                 // Field scala/runtime/ScalaRunTime$.MODULE$:Lscala/runtime/ScalaRunTime$;
         6: aload_1
         7: invokevirtual #39                 // Method scala/runtime/ScalaRunTime$.array_length:(Ljava/lang/Object;)I
        10: if_icmpge     35
        13: getstatic     #35                 // Field scala/runtime/ScalaRunTime$.MODULE$:Lscala/runtime/ScalaRunTime$;
        16: aload_2
        17: iload_3
        18: getstatic     #35                 // Field scala/runtime/ScalaRunTime$.MODULE$:Lscala/runtime/ScalaRunTime$;
        21: aload_1
        22: iload_3
        23: invokevirtual #43                 // Method scala/runtime/ScalaRunTime$.array_apply:(Ljava/lang/Object;I)Ljava/lang/Object;
        26: invokevirtual #47                 // Method scala/runtime/ScalaRunTime$.array_update:(Ljava/lang/Object;ILjava/lang/Object;)V
        29: iinc          3, 1
        32: goto          2
        35: return
      StackMapTable: number_of_entries = 2
        frame_type = 252 /* append */
          offset_delta = 2
          locals = [ int ]
        frame_type = 32 /* same */
      LineNumberTable:
        line 5: 0
        line 6: 2
        line 7: 13
        line 8: 29
        line 10: 35
      LocalVariableTable:
        Start  Length  Slot  Name   Signature
            2      34     3   idx   I
            0      36     0  this   LbcGen/Arrays/ArrayTestLib$;
            0      36     1   src   Ljava/lang/Object;
            0      36     2   dst   Ljava/lang/Object;
    Signature: #28                          // <T:Ljava/lang/Object;>(Ljava/lang/Object;Ljava/lang/Object;)V
    MethodParameters:
      Name                           Flags
      src                            final
      dst                            final
      InvokeReturnType: length = 0x9 (unknown attribute)
       00 01 00 17 4D 00 00 00 00
      MethodParameterType: length = 0xC (unknown attribute)
       00 02 6D 00 00 00 00 6D 00 00 00 00
      MethodTypeParameterCount: length = 0x2 (unknown attribute)
       00 01

  public <T extends java.lang.Object> int checksum(java.lang.Object);
    descriptor: (Ljava/lang/Object;)I
    flags: (0x0001) ACC_PUBLIC
    Code:
      stack=4, locals=4, args_size=2
         0: iconst_0
         1: istore_2
         2: iconst_0
         3: istore_3
         4: iload_3
         5: getstatic     #35                 // Field scala/runtime/ScalaRunTime$.MODULE$:Lscala/runtime/ScalaRunTime$;
         8: aload_1
         9: invokevirtual #39                 // Method scala/runtime/ScalaRunTime$.array_length:(Ljava/lang/Object;)I
        12: if_icmpge     35
        15: iload_2
        16: getstatic     #35                 // Field scala/runtime/ScalaRunTime$.MODULE$:Lscala/runtime/ScalaRunTime$;
        19: aload_1
        20: iload_3
        21: invokevirtual #43                 // Method scala/runtime/ScalaRunTime$.array_apply:(Ljava/lang/Object;I)Ljava/lang/Object;
        24: invokestatic  #58                 // Method scala/runtime/Statics.anyHash:(Ljava/lang/Object;)I
        27: iadd
        28: istore_2
        29: iinc          3, 1
        32: goto          4
        35: iload_2
        36: ireturn
      StackMapTable: number_of_entries = 2
        frame_type = 253 /* append */
          offset_delta = 4
          locals = [ int, int ]
        frame_type = 30 /* same */
      LineNumberTable:
        line 14: 0
        line 15: 2
        line 16: 4
        line 17: 15
        line 18: 29
        line 20: 35
      LocalVariableTable:
        Start  Length  Slot  Name   Signature
            2      35     2   sum   I
            4      33     3     i   I
            0      37     0  this   LbcGen/Arrays/ArrayTestLib$;
            0      37     1 array   Ljava/lang/Object;
    Signature: #52                          // <T:Ljava/lang/Object;>(Ljava/lang/Object;)I
    MethodParameters:
      Name                           Flags
      array                          final
      InvokeReturnType: length = 0x9 (unknown attribute)
       00 01 00 15 4D 00 00 00 00
      MethodParameterType: length = 0x7 (unknown attribute)
       00 01 6D 00 00 00 00
      MethodTypeParameterCount: length = 0x2 (unknown attribute)
       00 01
}
SourceFile: "ArrayTestLib.scala"
  Scala: length = 0x0 (unknown attribute)

